setup.py
callifile/__init__.py
callifile/callifile_functions.py
callifile.egg-info/PKG-INFO
callifile.egg-info/SOURCES.txt
callifile.egg-info/dependency_links.txt
callifile.egg-info/top_level.txt