Metadata-Version: 1.0
Name: callifile
Version: 2.0
Summary: Call all functions in a file
Home-page: https://github.com/jerabaul29/python_callifile
Author: jerabaul29
Author-email: jean.rblt@gmail.com
License: MIT
Platform: UNKNOWN
